[
  {
    "name": "Mark",
    "message": ":bedge: :madgelate:",
    "timestamp": 1729232239511
  },
  {
    "name": "Alex",
    "message": "wenas",
    "timestamp": 1729232265795
  },
  {
    "name": "Gabriel_Diacich",
    "message": "heyya",
    "timestamp": 1729232271729
  },
  {
    "name": "Alex",
    "message": "interesante lo de js",
    "timestamp": 1729232277797
  },
  {
    "name": "Alex",
    "message": "pero js no se usa para jueguitos,no?",
    "timestamp": 1729232296766
  },
  {
    "name": "Lx_Albert",
    "message": ";mierda;",
    "timestamp": 1729232307054
  },
  {
    "name": "Lx_Albert",
    "message": "this is fine",
    "timestamp": 1729232313559
  },
  {
    "name": "Alex",
    "message": "se aproxima el momento del sticker",
    "timestamp": 1729232329501
  },
  {
    "name": "Lx_Albert",
    "message": ":Fibsh_lacrimossa:",
    "timestamp": 1729232335735
  },
  {
    "name": "Alex",
    "message": ";clasebasededatos;",
    "timestamp": 1729232389036
  },
  {
    "name": "Alex",
    "message": "@Mark tu eres el de arriba a la izquierda",
    "timestamp": 1729232440913
  },
  {
    "name": "Alex",
    "message": "falta media clase, sabeis si Emily vendrá al final?",
    "timestamp": 1729232533707
  },
  {
    "name": "Gabriel",
    "message": "@Alex nadie hace juegos en js al menos de que sea para web entonces ahi si",
    "timestamp": 1729232558144
  },
  {
    "name": "Gabriel",
    "message": "por ejemplo un tetris",
    "timestamp": 1729232569920
  },
  {
    "name": "Lx_Albert",
    "message": "Friv.com",
    "timestamp": 1729232590701
  },
  {
    "name": "Lx_Albert",
    "message": ":le_cry:",
    "timestamp": 1729232595581
  },
  {
    "name": "Gabriel",
    "message": "friv?",
    "timestamp": 1729232598091
  },
  {
    "name": "Alex",
    "message": "aah, entiendo",
    "timestamp": 1729232610224
  },
  {
    "name": "Lx_Albert",
    "message": "pff una net relativamente antigua llena de juegos hechos en java y que Adobe launcher soportaba",
    "timestamp": 1729232614677
  },
  {
    "name": "Alex",
    "message": "no conoces friv? @Gabriel",
    "timestamp": 1729232624991
  },
  {
    "name": "Gabriel",
    "message": "no",
    "timestamp": 1729232645635
  },
  {
    "name": "Lx_Albert",
    "message": ":ghost_por_gay:",
    "timestamp": 1729232666287
  },
  {
    "name": "Alex",
    "message": "buah, la infancia, era mítica página con cientos de juegos (lo sigue siendo)",
    "timestamp": 1729232667841
  },
  {
    "name": "Lx_Albert",
    "message": "@Alex no",
    "timestamp": 1729232674431
  },
  {
    "name": "Alex",
    "message": "NO?",
    "timestamp": 1729232680354
  },
  {
    "name": "Lx_Albert",
    "message": "ahora friv parece un anuncio softporn",
    "timestamp": 1729232680383
  },
  {
    "name": "Alex",
    "message": "Y LO MALO?",
    "timestamp": 1729232688946
  },
  {
    "name": "Lx_Albert",
    "message": "._.",
    "timestamp": 1729232691623
  },
  {
    "name": "Alex",
    "message": "perdón por gritar",
    "timestamp": 1729232694850
  },
  {
    "name": "Lx_Albert",
    "message": "este pajin",
    "timestamp": 1729232695975
  },
  {
    "name": "Mercedes",
    "message": "Lo comprendeis?",
    "timestamp": 1729232737844
  },
  {
    "name": "Lx_Albert",
    "message": "Si mercedes, ya que alguien me mate",
    "timestamp": 1729232755136
  },
  {
    "name": "Lx_Albert",
    "message": "mi cuerpo ruega una 12x70 en toda la boca",
    "timestamp": 1729232768575
  },
  {
    "name": "Gabriel",
    "message": ";wall;",
    "timestamp": 1729232780255
  },
  {
    "name": "Lx_Albert",
    "message": ":moyai:",
    "timestamp": 1729232785152
  },
  {
    "name": "Alex",
    "message": "Gabriel buscando el emoji con la respuesta perfecta",
    "timestamp": 1729232788365
  },
  {
    "name": "Lx_Albert",
    "message": ":car:",
    "timestamp": 1729232811043
  },
  {
    "name": "Alex",
    "message": "nuestro delegado? el hombre ese tan guapo de alante",
    "timestamp": 1729232814023
  },
  {
    "name": "Mark",
    "message": ":hackerman:",
    "timestamp": 1729232816348
  },
  {
    "name": "Lx_Albert",
    "message": "*insert free-bird solo*",
    "timestamp": 1729232821395
  },
  {
    "name": "Alex",
    "message": "<input type=\"button\">",
    "timestamp": 1729232846409
  },
  {
    "name": "Gabriel",
    "message": "@Lx_Albert te imaginas meterle sonido de freebird?",
    "timestamp": 1729232856411
  },
  {
    "name": "Lx_Albert",
    "message": "seria un link hecho embed a otra pagina con esa huevada",
    "timestamp": 1729232873140
  },
  {
    "name": "Lx_Albert",
    "message": "JAJAJAJAJAJ",
    "timestamp": 1729232875124
  },
  {
    "name": "Lx_Albert",
    "message": ":tilin:",
    "timestamp": 1729232894116
  },
  {
    "name": "Gabriel",
    "message": ":epico:",
    "timestamp": 1729232900243
  },
  {
    "name": "Lx_Albert",
    "message": "eso tilin",
    "timestamp": 1729232907332
  },
  {
    "name": "Alex",
    "message": "<button>Si pulsas aquí te vuelves gay</button>",
    "timestamp": 1729232918933
  },
  {
    "name": "Alex",
    "message": "no funcionó :(",
    "timestamp": 1729232926253
  },
  {
    "name": "Gabriel",
    "message": ":LOSER:ç",
    "timestamp": 1729232930879
  },
  {
    "name": "Lx_Albert",
    "message": "*a href=\"e621.net\"*",
    "timestamp": 1729232949504
  },
  {
    "name": "Lx_Albert",
    "message": ":overthinking:",
    "timestamp": 1729232965344
  },
  {
    "name": "Gabriel",
    "message": "la de poner <",
    "timestamp": 1729232978400
  },
  {
    "name": "Lx_Albert",
    "message": "era una ironia",
    "timestamp": 1729232984233
  },
  {
    "name": "Lx_Albert",
    "message": "del link de Alex",
    "timestamp": 1729232988649
  },
  {
    "name": "Alex",
    "message": "<button class=\"button id=\"enviar\" style=\"height: 34px; margin-right: 0px;\">\n          Si pulsas aquí te vuelves gay\n        </button>",
    "timestamp": 1729232999479
  },
  {
    "name": "Lx_Albert",
    "message": "ingaturroña",
    "timestamp": 1729233005817
  },
  {
    "name": "Alex",
    "message": "ay va, no funciona",
    "timestamp": 1729233012471
  },
  {
    "name": "Alex",
    "message": "venga a trabajar (wtf)",
    "timestamp": 1729233021951
  },
  {
    "name": "Gabriel",
    "message": "la id tiene que ser unica xD",
    "timestamp": 1729233023113
  },
  {
    "name": "Lx_Albert",
    "message": ";yo_la_conoci_en_un_taxi; :yo_la_conoci_en_un_taxi: :yo_la_conoci_en_un_taxi: ;yo_la_conoci_en_un_taxi;",
    "timestamp": 1729233039065
  },
  {
    "name": "Alex",
    "message": "vamos a hacer base de datos en writer",
    "timestamp": 1729233039536
  },
  {
    "name": "Lx_Albert",
    "message": "yo la conoci en un tasi  :yo_la_conoci_en_un_taxi:",
    "timestamp": 1729233064009
  },
  {
    "name": "Alex",
    "message": "para que cuando haga el juego de las yanderes, pueda conectar la base de datos de libre office writer al juego.",
    "timestamp": 1729233070327
  },
  {
    "name": "Lx_Albert",
    "message": "de camino al clob :yo_la_conoci_en_un_taxi:",
    "timestamp": 1729233073569
  },
  {
    "name": "Lx_Albert",
    "message": "yo la conoci en un tasi :yo_la_conoci_en_un_taxi:",
    "timestamp": 1729233080649
  },
  {
    "name": "Mercedes",
    "message": "Porque falta tanta gente hoy aquí?",
    "timestamp": 1729233085200
  },
  {
    "name": "Lx_Albert",
    "message": "de camino al cloooooooooob",
    "timestamp": 1729233087369
  },
  {
    "name": "Lx_Albert",
    "message": ":yo_la_conoci_en_un_taxi:",
    "timestamp": 1729233088105
  },
  {
    "name": "Gabriel",
    "message": ":catjam:",
    "timestamp": 1729233089329
  },
  {
    "name": "Lx_Albert",
    "message": "me lo paro :yo_la_conoci_en_un_taxi:",
    "timestamp": 1729233091265
  },
  {
    "name": "Lx_Albert",
    "message": "el tasi :yo_la_conoci_en_un_taxi:",
    "timestamp": 1729233093961
  },
  {
    "name": "Lx_Albert",
    "message": "me lo paro :yo_la_conoci_en_un_taxi:",
    "timestamp": 1729233096185
  },
  {
    "name": "Lx_Albert",
    "message": "el tasi :yo_la_conoci_en_un_taxi:",
    "timestamp": 1729233097793
  },
  {
    "name": "Lx_Albert",
    "message": "XD",
    "timestamp": 1729233099505
  },
  {
    "name": "Mark",
    "message": "Carlos, el de los huevos largos",
    "timestamp": 1729233124959
  },
  {
    "name": "Lx_Albert",
    "message": "@Alex que juego de yanderes oye loco ctm",
    "timestamp": 1729233129139
  },
  {
    "name": "Lx_Albert",
    "message": "no tenias suficiente con el yandere Sim?",
    "timestamp": 1729233141898
  },
  {
    "name": "Alex",
    "message": "NO! YANDERE SIM ES DESDE LA PESPECTIVA DE LA YANDERE, y como persona sumisa amante de las yanderes , prefiere la otra pespectiva",
    "timestamp": 1729233189481
  },
  {
    "name": "Lx_Albert",
    "message": ":simp:",
    "timestamp": 1729233197619
  },
  {
    "name": "Lx_Albert",
    "message": "Te voy a hacer un mod de fnf por esa webada",
    "timestamp": 1729233210450
  },
  {
    "name": "Alex",
    "message": "nono",
    "timestamp": 1729233236254
  },
  {
    "name": "Alex",
    "message": "fnf",
    "timestamp": 1729233237419
  },
  {
    "name": "Alex",
    "message": "yo quiero juegos 3d",
    "timestamp": 1729233242922
  },
  {
    "name": "Lx_Albert",
    "message": "un mod de fnaf",
    "timestamp": 1729233249105
  },
  {
    "name": "Lx_Albert",
    "message": ":v",
    "timestamp": 1729233249761
  },
  {
    "name": "Alex",
    "message": "@Gabriel te pago 20 pavos si me haces un juego de yanderes",
    "timestamp": 1729233263258
  },
  {
    "name": "Lx_Albert",
    "message": "wn no es lo peor que te pueden hacer, a mi en discord me dibujaron embarazado y porno gay :'v",
    "timestamp": 1729233275137
  },
  {
    "name": "Lx_Albert",
    "message": "mi pobre fursona qwq",
    "timestamp": 1729233285825
  },
  {
    "name": "Lx_Albert",
    "message": ":hijos_de_su_puta_madre:",
    "timestamp": 1729233290505
  },
  {
    "name": "Alex",
    "message": "@Mark te pago 5 si te pones un traje de maid",
    "timestamp": 1729233290873
  },
  {
    "name": "Lx_Albert",
    "message": "YOYOOYOYOy",
    "timestamp": 1729233294409
  },
  {
    "name": "Lx_Albert",
    "message": "CAP CAP CAP",
    "timestamp": 1729233296753
  },
  {
    "name": "Lx_Albert",
    "message": "@Mark  PONTE FALDITA",
    "timestamp": 1729233304793
  },
  {
    "name": "Lx_Albert",
    "message": ":cleaning:",
    "timestamp": 1729233427229
  },
  {
    "name": "Gabriel",
    "message": "@Alex 20€ por un juego ni te hago el codigo fuente. hay que tirar mas pa arriba que un juego cuesta mucho",
    "timestamp": 1729233446535
  },
  {
    "name": "Alex",
    "message": "@Gabriel voy mal de presupuesto",
    "timestamp": 1729233515309
  },
  {
    "name": "Gabriel",
    "message": "no es mi problema",
    "timestamp": 1729233526235
  },
  {
    "name": "Alex",
    "message": "piensa que seguramente no sea el único degenerado que quiera uno",
    "timestamp": 1729233534139
  },
  {
    "name": "Alex",
    "message": "en itchi.io hay muchos",
    "timestamp": 1729233541827
  },
  {
    "name": "casal",
    "message": "@Derek mira DC",
    "timestamp": 1729233621003
  },
  {
    "name": "Mark",
    "message": ":hackerman:",
    "timestamp": 1729233698622
  },
  {
    "name": "casal",
    "message": ":mierda:",
    "timestamp": 1729233839594
  }
]